pspartition.cpython-37m-darwin.so
pspartition-0.7.post5.dist-info/METADATA
pspartition-0.7.post5.dist-info/WHEEL
pspartition-0.7.post5.dist-info/top_level.txt
pspartition-0.7.post5.dist-info/RECORD
