Metadata-Version: 2.1
Name: pspartition
Version: 0.7.post5
Summary: a hierachical clustering algorithm based on information theory
Home-page: https://github.com/zhaofeng-shu33/principal_sequence_of_partition
Author: zhaofeng-shu33
Author-email: 616545598@qq.com
License: Apache License Version 2.0
Platform: UNKNOWN
Classifier: Programming Language :: Python :: 3
